{
  "qid": 11419,
  "question": "What does the term \"Wakhi\" refer to?",
  "ambiguous_entity": "Wakhi",
  "content": {
    "source_1": "Ishkashim, to the upper reaches of the Wakhan River. In Tajikistan the Wakhi and other communities that speak one of the Pamir languages refer to themselves as Pamiri or Badakhshani and there has been a movement to separate their identity from that of the majority Persian-speaking Tajiks. Linguists universally refer to Wakhi as an East Iranian language independent of Tajik Persian, but many Tajik nationalists insist that Wakhi and other Pamir languages are actually dialects of Tajik. In Gilgit-Baltistan Wakhi is spoken in the sparsely populated upper portions of five of the northernmost valleys: Hunza (many ethnic Wakhi of this",
    "source_2": "Wakhi people The Wakhi people, or the Khik, are an ethnic group living in adjacent, remote regions of Afghanistan, Tajikistan, Pakistan, and China. They are predominantly centered in Afghanistan's Wakhan Corridor, the northern-most part of Pakistan's Gilgit-Baltistan, the Gorno-Badakhshan region of Tajikistan, and the southwestern region of China's Xinjiang. They are native speakers of Wakhi, an Indo-European language of the Iranian branch. The Wakhi people refer to themselves as \"Khik\" and to their language as \"Khik zik\". The exonym \"Wakhī\", which is given to them by their neighbors, is based on \"Wux̌\", the local name of the region of Wakhan,"
  },
  "content_pid": [
    "3529299",
    "3529810"
  ],
  "answer": [
    "Language",
    "An ethnic group"
  ]
}